CHANGELOG.rst
LICENSE
MANIFEST.in
README.rst
setup.cfg
setup.py
flask_apispec/__init__.py
flask_apispec/annotations.py
flask_apispec/apidoc.py
flask_apispec/extension.py
flask_apispec/paths.py
flask_apispec/utils.py
flask_apispec/views.py
flask_apispec/wrapper.py
flask_apispec/__pycache__/__init__.cpython-310.pyc
flask_apispec/__pycache__/annotations.cpython-310.pyc
flask_apispec/__pycache__/apidoc.cpython-310.pyc
flask_apispec/__pycache__/extension.cpython-310.pyc
flask_apispec/__pycache__/paths.cpython-310.pyc
flask_apispec/__pycache__/utils.cpython-310.pyc
flask_apispec/__pycache__/views.cpython-310.pyc
flask_apispec/__pycache__/wrapper.cpython-310.pyc
flask_apispec/templates/apidoc.html
flask_apispec_hyper.egg-info/PKG-INFO
flask_apispec_hyper.egg-info/SOURCES.txt
flask_apispec_hyper.egg-info/dependency_links.txt
flask_apispec_hyper.egg-info/not-zip-safe
flask_apispec_hyper.egg-info/requires.txt
flask_apispec_hyper.egg-info/top_level.txt
tests/test_extension.py
tests/test_openapi.py
tests/test_paths.py
tests/test_utils.py
tests/test_views.py