Metadata-Version: 2.1
Name: flask-apispec-hyper
Version: 0.12.0
Summary: Build and document REST APIs with Flask and apispec
Home-page: https://github.com/hyperflask/flask-apispec-hyper
Author: Joshua Carp
Author-email: jm.carp@gmail.com
License: MIT
Project-URL: Bug Reports, https://github.com/hyperflask/flask-apispec-hyper/issues
Project-URL: Changelog, https://flask-apispec.readthedocs.io/en/latest/changelog.html
Keywords: flask marshmallow webargs apispec
Requires-Python: >=3.8
License-File: LICENSE
Requires-Dist: flask>=0.10.1
Requires-Dist: marshmallow>=3.0.0
Requires-Dist: webargs>=6.0.0
Requires-Dist: apispec>=4.0.0
